build/lib/probeplanner/__init__.py
build/lib/probeplanner/_probe.py
build/lib/probeplanner/cli.py
build/lib/probeplanner/core.py
build/lib/probeplanner/hierarchy.py
build/lib/probeplanner/planner.py
build/lib/probeplanner/probe.py
build/lib/probeplanner/terminal_ui.py
build/lib/probeplanner/ui.py
build/lib/probeplanner/viewer.py
probeplanner/__init__.py
probeplanner/_probe.py
probeplanner/cli.py
probeplanner/core.py
probeplanner/hierarchy.py
probeplanner/planner.py
probeplanner/probe.py
probeplanner/terminal_ui.py
probeplanner/ui.py
probeplanner/viewer.py
probeplanner-0.1.5.dist-info/LICENSE
probeplanner-0.1.5.dist-info/METADATA
probeplanner-0.1.5.dist-info/WHEEL
probeplanner-0.1.5.dist-info/entry_points.txt
probeplanner-0.1.5.dist-info/top_level.txt
probeplanner-0.1.5.dist-info/RECORD
