Metadata-Version: 2.1
Name: probeplanner
Version: 0.1.5
Summary: Plan probe locations
Home-page: https://github.com/brainglobe/probeplanner
Author: Federico Claudi
License: UNKNOWN
Platform: UNKNOWN
Classifier: Development Status :: 3 - Alpha
Classifier: Operating System :: POSIX :: Linux
Classifier: Operating System :: Microsoft :: Windows :: Windows 10
Classifier: Operating System :: MacOS :: MacOS X
Classifier: Programming Language :: Python
Classifier: Programming Language :: Python :: 3.6
Classifier: Programming Language :: Python :: 3.7
Classifier: Programming Language :: Python :: 3.8
Classifier: Intended Audience :: Developers
Classifier: Intended Audience :: Science/Research
Requires-Python: >=3.6
Requires-Dist: brainrender (>=2.0.2.0)
Requires-Dist: rich (>=9.12.0)
Requires-Dist: myterial
Requires-Dist: loguru
Requires-Dist: typer
Requires-Dist: pyyaml
